<annotation>
	<folder>Crack Img trial 1_18032019</folder>
	<filename>IMG_20190314_143931.jpg</filename>
	<path>E:\LUKMAN MANSURI\My Research\Crack Detection Trial 1 18032019\Crack Img trial 1_18032019\IMG_20190314_143931.jpg</path>
	<source>
		<database>Unknown</database>
	</source>
	<size>
		<width>2448</width>
		<height>3264</height>
		<depth>3</depth>
	</size>
	<segmented>0</segmented>
	<object>
		<name>Crack</name>
		<pose>Unspecified</pose>
		<truncated>0</truncated>
		<difficult>0</difficult>
		<bndbox>
			<xmin>89</xmin>
			<ymin>1840</ymin>
			<xmax>401</xmax>
			<ymax>2356</ymax>
		</bndbox>
	</object>
	<object>
		<name>Crack</name>
		<pose>Unspecified</pose>
		<truncated>0</truncated>
		<difficult>0</difficult>
		<bndbox>
			<xmin>734</xmin>
			<ymin>1427</ymin>
			<xmax>1184</xmax>
			<ymax>1560</ymax>
		</bndbox>
	</object>
	<object>
		<name>Crack</name>
		<pose>Unspecified</pose>
		<truncated>0</truncated>
		<difficult>0</difficult>
		<bndbox>
			<xmin>1209</xmin>
			<ymin>1069</ymin>
			<xmax>1389</xmax>
			<ymax>1423</ymax>
		</bndbox>
	</object>
	<object>
		<name>Crack</name>
		<pose>Unspecified</pose>
		<truncated>0</truncated>
		<difficult>0</difficult>
		<bndbox>
			<xmin>1397</xmin>
			<ymin>244</ymin>
			<xmax>2430</xmax>
			<ymax>1035</ymax>
		</bndbox>
	</object>
</annotation>
